python_orbeon_layout/__init__.py
python_orbeon_layout/context.py
python_orbeon_layout/example_data.py
python_orbeon_layout/main.py
python_orbeon_layout/utils.py
python_orbeon_layout/contents/fonts/MYRIADPRO-BOLD.OTF
python_orbeon_layout/contents/fonts/MYRIADPRO-BOLDCOND.OTF
python_orbeon_layout/contents/fonts/MYRIADPRO-BOLDCONDIT.OTF
python_orbeon_layout/contents/fonts/MYRIADPRO-BOLDIT.OTF
python_orbeon_layout/contents/fonts/MYRIADPRO-COND.OTF
python_orbeon_layout/contents/fonts/MYRIADPRO-CONDIT.OTF
python_orbeon_layout/contents/fonts/MYRIADPRO-REGULAR.OTF
python_orbeon_layout/contents/fonts/MYRIADPRO-SEMIBOLD.OTF
python_orbeon_layout/contents/fonts/MYRIADPRO-SEMIBOLDIT.OTF
python_orbeon_layout/contents/fonts/MyriadPro-Light.otf
python_orbeon_layout/regions/__init__.py
python_orbeon_layout/regions/body.py
python_orbeon_layout/regions/cliente_responsavel.py
python_orbeon_layout/regions/data_inicio_conclusao.py
python_orbeon_layout/regions/financial.py
python_orbeon_layout/regions/logo.py
python_orbeon_layout/regions/sales_order_id_and_layout_id.py
python_orbeon_layout/regions/shipping.py
tests/__init__.py
tests/test_draw.py
python_orbeon_layout-1.0.4.dist-info/LICENSE
python_orbeon_layout-1.0.4.dist-info/METADATA
python_orbeon_layout-1.0.4.dist-info/WHEEL
python_orbeon_layout-1.0.4.dist-info/top_level.txt
python_orbeon_layout-1.0.4.dist-info/RECORD
